setup.cfg
setup.py
abl/__init__.py
abl.cssprocessor.egg-info/PKG-INFO
abl.cssprocessor.egg-info/SOURCES.txt
abl.cssprocessor.egg-info/dependency_links.txt
abl.cssprocessor.egg-info/entry_points.txt
abl.cssprocessor.egg-info/namespace_packages.txt
abl.cssprocessor.egg-info/requires.txt
abl.cssprocessor.egg-info/top_level.txt
abl/cssprocessor/__init__.py
abl/cssprocessor/parser.py
abl/cssprocessor/rewriter.py
abl/cssprocessor/util.py
abl/cssprocessor/validator.py