Metadata-Version: 1.0
Name: abl.cssprocessor
Version: 0.2
Summary: A processor to aggregate CSS-files and their referenced media
Home-page: UNKNOWN
Author: Diez B. Roggisch
Author-email: diez.roggisch@ableton.com
License: MIT
Platform: UNKNOWN
Classifier: Development Status :: 5 - Production/Stable
Classifier: Environment :: Web Environment
Classifier: Environment :: Web Environment :: ToscaWidgets
Classifier: Topic :: Software Development :: Libraries :: Python Modules
Classifier: Topic :: Software Development :: Widget Sets
Classifier: Intended Audience :: Developers
Classifier: Operating System :: OS Independent
Classifier: Programming Language :: Python
